coola/__init__.py
coola/comparison.py
coola/py.typed
coola/reduction.py
coola/summarization.py
coola/testing.py
coola/equality/__init__.py
coola/equality/config.py
coola/equality/comparators/__init__.py
coola/equality/comparators/base.py
coola/equality/comparators/collection.py
coola/equality/comparators/default.py
coola/equality/comparators/jax_.py
coola/equality/comparators/numpy_.py
coola/equality/comparators/pandas_.py
coola/equality/comparators/polars_.py
coola/equality/comparators/pyarrow_.py
coola/equality/comparators/scalar.py
coola/equality/comparators/torch_.py
coola/equality/comparators/utils.py
coola/equality/comparators/xarray_.py
coola/equality/handlers/__init__.py
coola/equality/handlers/base.py
coola/equality/handlers/data.py
coola/equality/handlers/dtype.py
coola/equality/handlers/equal.py
coola/equality/handlers/jax_.py
coola/equality/handlers/mapping.py
coola/equality/handlers/native.py
coola/equality/handlers/numpy_.py
coola/equality/handlers/pandas_.py
coola/equality/handlers/polars_.py
coola/equality/handlers/pyarrow_.py
coola/equality/handlers/scalar.py
coola/equality/handlers/sequence.py
coola/equality/handlers/shape.py
coola/equality/handlers/torch_.py
coola/equality/testers/__init__.py
coola/equality/testers/base.py
coola/equality/testers/default.py
coola/formatters/__init__.py
coola/formatters/base.py
coola/formatters/default.py
coola/formatters/numpy_.py
coola/formatters/torch_.py
coola/iterator/__init__.py
coola/iterator/filtering.py
coola/iterator/bfs/__init__.py
coola/iterator/bfs/base.py
coola/iterator/bfs/default.py
coola/iterator/bfs/interface.py
coola/iterator/bfs/iterable.py
coola/iterator/bfs/mapping.py
coola/iterator/bfs/registry.py
coola/iterator/dfs/__init__.py
coola/iterator/dfs/base.py
coola/iterator/dfs/default.py
coola/iterator/dfs/interface.py
coola/iterator/dfs/iterable.py
coola/iterator/dfs/mapping.py
coola/iterator/dfs/registry.py
coola/nested/__init__.py
coola/nested/conversion.py
coola/nested/mapping.py
coola-0.11.1.dist-info/METADATA
coola-0.11.1.dist-info/WHEEL
coola-0.11.1.dist-info/licenses/LICENSE
coola-0.11.1.dist-info/RECORD
