Metadata-Version: 2.4
Name: coola
Version: 0.11.1
Dynamic: Maintainer
Dynamic: Maintainer-email
Summary: Library to check equality between two complex/nested objects
Project-URL: Homepage, https://github.com/durandtibo/coola
Project-URL: Repository, https://github.com/durandtibo/coola
Project-URL: Documentation, https://durandtibo.github.io/coola/
Project-URL: Changelog, https://github.com/durandtibo/coola/releases
Project-URL: Issues, https://github.com/durandtibo/coola/issues
Author-email: Thibaut Durand <durand.tibo+gh@gmail.com>
License-Expression: BSD-3-Clause
License-File: LICENSE
Keywords: equality,jax,numpy,pandas,polars,pyarrow,pytorch,testing,xarray
Classifier: Development Status :: 4 - Beta
Classifier: Intended Audience :: Developers
Classifier: Intended Audience :: Science/Research
Classifier: License :: OSI Approved :: BSD License
Classifier: Operating System :: MacOS
Classifier: Operating System :: POSIX :: Linux
Classifier: Programming Language :: Python :: 3.10
Classifier: Programming Language :: Python :: 3.11
Classifier: Programming Language :: Python :: 3.12
Classifier: Programming Language :: Python :: 3.13
Classifier: Programming Language :: Python :: 3.14
Classifier: Topic :: Scientific/Engineering
Classifier: Topic :: Software Development :: Libraries
Classifier: Topic :: Software Development :: Testing
Requires-Python: >=3.10
Provides-Extra: all
Requires-Dist: jax<1.0,>=0.5.0; (sys_platform == 'linux' or (sys_platform == 'darwin' and platform_machine == 'arm64')) and extra == 'all'
Requires-Dist: numpy<3.0,>=1.24; extra == 'all'
Requires-Dist: packaging>=22.0; extra == 'all'
Requires-Dist: pandas<3.0,>=2.0; extra == 'all'
Requires-Dist: polars<2.0,>=1.0; extra == 'all'
Requires-Dist: pyarrow<23.0,>=11.0; (python_version < '3.14') and extra == 'all'
Requires-Dist: torch<3.0,>=2.0; (sys_platform == 'linux' or (sys_platform == 'darwin' and platform_machine == 'arm64')) and extra == 'all'
Requires-Dist: xarray>=2024.1; extra == 'all'
Provides-Extra: jax
Requires-Dist: jax<1.0,>=0.5.0; (sys_platform == 'linux' or (sys_platform == 'darwin' and platform_machine == 'arm64')) and extra == 'jax'
Provides-Extra: numpy
Requires-Dist: numpy<3.0,>=1.24; extra == 'numpy'
Provides-Extra: packaging
Requires-Dist: packaging>=22.0; extra == 'packaging'
Provides-Extra: pandas
Requires-Dist: pandas<3.0,>=2.0; extra == 'pandas'
Provides-Extra: polars
Requires-Dist: polars<2.0,>=1.0; extra == 'polars'
Provides-Extra: pyarrow
Requires-Dist: pyarrow<23.0,>=11.0; (python_version < '3.14') and extra == 'pyarrow'
Provides-Extra: torch
Requires-Dist: torch<3.0,>=2.0; (sys_platform == 'linux' or (sys_platform == 'darwin' and platform_machine == 'arm64')) and extra == 'torch'
Provides-Extra: xarray
Requires-Dist: xarray>=2024.1; extra == 'xarray'
